{
    "title": "Minecraft FULL SOUNDTRACK (2016)",
    "performer": "Luigi",
    "file": {
        "path": "https://www.youtube.com/watch?v=Dg0IjOzopYU",
        "type": "MP3"
    },
    "tracks": [
        {
            "title": "Key",
            "time": 0,
            "index": "00:00:00"
        },
        {
            "title": "Subwoofer Lullaby",
            "time": 64,
            "index": "01:04:00"
        },
        {
            "title": "Living Mice",
            "time": 280,
            "index": "04:40:00"
        },
        {
            "title": "Haggstrom",
            "time": 450,
            "index": "07:30:00"
        },
        {
            "title": "Minecraft",
            "time": 653,
            "index": "10:53:00"
        },
        {
            "title": "Oxygene",
            "time": 908,
            "index": "15:08:00"
        },
        {
            "title": "Mice on Venus",
            "time": 974,
            "index": "16:14:00"
        },
        {
            "title": "Dry Hands",
            "time": 1268,
            "index": "21:08:00"
        },
        {
            "title": "Wet Hands",
            "time": 1324,
            "index": "22:04:00"
        },
        {
            "title": "Clark",
            "time": 1414,
            "index": "23:34:00"
        },
        {
            "title": "Sweden",
            "time": 1606,
            "index": "26:46:00"
        },
        {
            "title": "Danny",
            "time": 1821,
            "index": "30:21:00"
        },
        {
            "title": "Biome Fest",
            "time": 2078,
            "index": "34:38:00"
        },
        {
            "title": "Blind Spots",
            "time": 2458,
            "index": "40:58:00"
        },
        {
            "title": "Haunt Muskie",
            "time": 2794,
            "index": "46:34:00"
        },
        {
            "title": "Aria Math",
            "time": 3152,
            "index": "52:32:00"
        },
        {
            "title": "Dreiton",
            "time": 3474,
            "index": "57:54:00"
        },
        {
            "title": "Taswell",
            "time": 3965,
            "index": "66:05:00"
        },
        {
            "title": "Mutation",
            "time": 4472,
            "index": "74:32:00"
        },
        {
            "title": "Moog City 2",
            "time": 4666,
            "index": "77:46:00"
        },
        {
            "title": "Beginning 2",
            "time": 4852,
            "index": "80:52:00"
        },
        {
            "title": "Floating Trees",
            "time": 5036,
            "index": "83:56:00"
        },
        {
            "title": "Concrete Halls",
            "time": 5281,
            "index": "88:01:00"
        },
        {
            "title": "Dead Voxel",
            "time": 5542,
            "index": "92:22:00"
        },
        {
            "title": "Warmth",
            "time": 5844,
            "index": "97:24:00"
        },
        {
            "title": "Ballad of the Cats",
            "time": 6088,
            "index": "101:28:00"
        },
        {
            "title": "Boss",
            "time": 6363,
            "index": "106:03:00"
        },
        {
            "title": "End",
            "time": 6708,
            "index": "111:48:00"
        }
    ]
}